magic_storage/__init__.py
magic_storage/_atomic_file.py
magic_storage/_magic.py
magic_storage/_store_type.py
magic_storage/_utils.py
magic_storage/base/__init__.py
magic_storage/base/_deleter.py
magic_storage/base/_reader.py
magic_storage/base/_storage_io.py
magic_storage/base/_writer.py
magic_storage/impl/__init__.py
magic_storage/impl/_filesystem.py
magic_storage/impl/_memory.py
magic_storage/mixins/__init__.py
magic_storage/mixins/_cache_if_missing.py
magic_storage-1.1.0.dist-info/AUTHORS
magic_storage-1.1.0.dist-info/LICENSE
magic_storage-1.1.0.dist-info/METADATA
magic_storage-1.1.0.dist-info/WHEEL
magic_storage-1.1.0.dist-info/top_level.txt
magic_storage-1.1.0.dist-info/RECORD
